fastqlapi-0.3.8.dist-info/METADATA
fastqlapi-0.3.8.dist-info/WHEEL
fastqlapi-0.3.8.dist-info/license_files/LICENSE
fastqlapi/LICENSE
fastqlapi/newscript.py
fastqlapi/server.py
fastqlapi/test_schema.py
fastqlapi/__init__.py
fastqlapi/fastqlapi.pyd
fastqlapi-0.3.8.dist-info/RECORD
