Metadata-Version: 2.1
Name: fastqlapi
Version: 0.3.8
Classifier: Programming Language :: Rust
Classifier: Programming Language :: Python :: Implementation :: CPython
Classifier: Programming Language :: Python :: Implementation :: PyPy
Requires-Dist: zmq
License-File: LICENSE
Requires-Python: >=3.7
